scireadability/__init__.py
scireadability/dictionary_utils.py
scireadability/scireadability.py
scireadability/resources/en/cmudict.dict
scireadability/resources/en/custom_dict.json
scireadability/resources/en/easy_words.txt
scireadability-2.0.1.dist-info/licenses/LICENSE
scireadability-2.0.1.dist-info/METADATA
scireadability-2.0.1.dist-info/WHEEL
scireadability-2.0.1.dist-info/top_level.txt
scireadability-2.0.1.dist-info/RECORD
