Metadata-Version: 2.4
Name: scireadability
Version: 2.0.1
Summary: Calculate statistical features from text, mainly scientific literature
Home-page: https://github.com/robert-roth/scireadability
Author: Robert Roth
Author-email: rwroth5@gmail.com
License: MIT
Project-URL: Documentation, https://github.com/robert-roth/scireadability
Project-URL: Demo, https://scireadability-rwroth5.pythonanywhere.com/analyze/
Classifier: Programming Language :: Python
Classifier: Programming Language :: Python :: 3.12
Classifier: Programming Language :: Python :: 3.11
Classifier: Programming Language :: Python :: 3.10
Classifier: Programming Language :: Python :: 3 :: Only
Classifier: Intended Audience :: Developers
Classifier: Intended Audience :: Education
Classifier: Intended Audience :: Science/Research
Classifier: Topic :: Text Processing
Requires-Python: >=3.10
License-File: LICENSE
Requires-Dist: setuptools
Requires-Dist: appdirs
Dynamic: author
Dynamic: author-email
Dynamic: classifier
Dynamic: description
Dynamic: description-content-type
Dynamic: home-page
Dynamic: license
Dynamic: license-file
Dynamic: project-url
Dynamic: requires-dist
Dynamic: requires-python
Dynamic: summary
